singleton/__init__.py
singleton/package_data.dat
singleton/singleton.py
singleton_package-0.8.2.dist-info/licenses/LICENSE.txt
singleton_package-0.8.2.dist-info/METADATA
singleton_package-0.8.2.dist-info/WHEEL
singleton_package-0.8.2.dist-info/top_level.txt
singleton_package-0.8.2.dist-info/RECORD
