Metadata-Version: 2.4
Name: singleton_package
Version: 0.8.2
Summary: A simple Python package to create singleton objects
Author-email: Mahdi Kiani <mahdikiany@gmail.com>
Maintainer-email: Mahdi Kiani <mahdikiany@gmail.com>
License: Copyright (c) 2024 Mahdi Kiani
Project-URL: Homepage, https://github.com/mahdikiani/singleton_package
Project-URL: Bug Reports, https://github.com/mahdikiani/singleton_package/issues
Project-URL: Say Thanks!, https://saythanks.io/to/mahdikiani
Project-URL: Source, https://github.com/mahdikiani/singleton_package
Keywords: singleton,design pattern
Classifier: Development Status :: 5 - Production/Stable
Classifier: Intended Audience :: Developers
Classifier: Topic :: Software Development :: Build Tools
Classifier: License :: OSI Approved :: MIT License
Classifier: Programming Language :: Python :: 3
Classifier: Programming Language :: Python :: 3.8
Classifier: Programming Language :: Python :: 3.9
Classifier: Programming Language :: Python :: 3.10
Classifier: Programming Language :: Python :: 3.11
Classifier: Programming Language :: Python :: 3.12
Classifier: Programming Language :: Python :: 3 :: Only
Classifier: Typing :: Typed
Requires-Python: >=3
License-File: LICENSE.txt
Provides-Extra: dev
Requires-Dist: check-manifest; extra == "dev"
Provides-Extra: test
Requires-Dist: coverage; extra == "test"
Dynamic: license-file
